Workbook

Sheet Matriz de Pugh
A1: GPIO Génesis — Matriz de Pugh (semana 6)
A2: Datum: C1 — Planta en corte. Celdas en azul con fondo amarillo = evaluación (+ / - / S); todo lo demás se calcula. Pesos definidos antes de evaluar.
A4: ID | B4: Criterio | C4: Tipo | D4: Peso | E4: Descripción | F4: C1 — Planta en corte (datum) | G4: C2 — Sala de control | H4: C3 — Primer turno | I4: Puntos C2 | J4: Puntos C3 | K4: Justificación C2 | L4: Justificación C3
A5: D1 | B5: Pin ↔ máquina legible | C5: Deseabilidad | D5: 0.15 | E5: Sin leer el tutorial, se entiende qué pin mueve qué máquina. | F5: datum | G5: - | H5: - | I5: =IF(G5="+",1,IF(G5="-",-1,0))*$D5 -> -0.15 | J5: =IF(H5="+",1,IF(H5="-",-1,0))*$D5 -> -0.15 | K5: Las etiquetas D5/D2/D4 flotan lejos de las máquinas; en la evaluación del equipo C1 fue el más claro. | L5: El render no muestra el pin junto al motor; el nombre MOTOR_BANDA solo está en el código.
A6: D2 | B6: Estado visible de un vistazo | C6: Deseabilidad | D6: 0.15 | E6: Se distingue si la planta funciona y qué máquina falla, sin abrir la consola. | F6: datum | G6: - | H6: - | I6: =IF(G6="+",1,IF(G6="-",-1,0))*$D6 -> -0.15 | J6: =IF(H6="+",1,IF(H6="-",-1,0))*$D6 -> -0.15 | K6: 'Todo gris = todo bien' no se lee así; la mini-traza de D5 salió como pulso aunque el pin está en HIGH. | L6: El estado depende de mantener Alt; el tablero '3 de 3' ayuda. El equipo lo puso 2.º después de C1.
A7: D3 | B7: Se siente juego, no clase | C7: Deseabilidad | D7: 0.15 | E7: Atractivo para un jugador de Minecraft/simuladores; ganas de volver. | F7: datum | G7: - | H7: + | I7: =IF(G7="+",1,IF(G7="-",-1,0))*$D7 -> -0.15 | J7: =IF(H7="+",1,IF(H7="-",-1,0))*$D7 -> 0.15 | K7: Fue el que menos gustó: frío, parece diagrama técnico; no hay drones en pantalla. | L7: Fue el que más gustó: pixel art cálido, luces, personaje amable que no se ve infantil.
A8: D4 | B8: Primeros 30 s sin instrucciones | C8: Deseabilidad | D8: 0.1 | E8: Llegar a la primera compilación que mueve algo sin ayuda (RI-01). | F8: datum | G8: - | H8: + | I8: =IF(G8="+",1,IF(G8="-",-1,0))*$D8 -> -0.1 | J8: =IF(H8="+",1,IF(H8="-",-1,0))*$D8 -> 0.1 | K8: Pantalla de arranque + interruptor Taller/Planta = un paso y un concepto extra antes de compilar. | L8: Arranque al 90%: una sola línea y una sola acción resaltada.
A9: F1 | B9: Horas de producción | C9: Factibilidad | D9: 0.15 | E9: Horas-persona para nivel 1 + menú (estimación de la tabla morfológica). | F9: datum | G9: - | H9: - | I9: =IF(G9="+",1,IF(G9="-",-1,0))*$D9 -> -0.15 | J9: =IF(H9="+",1,IF(H9="-",-1,0))*$D9 -> -0.15 | K9: ~104 h vs. ~67 h del datum. | L9: ~88 h vs. ~67 h del datum.
A10: F2 | B10: Riesgo técnico en Godot 4 | C10: Factibilidad | D10: 0.1 | E10: Dependencia de sistemas difíciles (validador de estado esperado, análisis de llamadas al HAL). | F10: datum | G10: - | H10: S | I10: =IF(G10="+",1,IF(G10="-",-1,0))*$D10 -> -0.1 | J10: =IF(H10="+",1,IF(H10="-",-1,0))*$D10 -> 0 | K10: 4E y 5C dependen de comparar estado esperado vs. real y de parsear el código. | L10: Plantilla con constantes y globos de diálogo son sencillos; mismo riesgo que el datum.
A11: F3 | B11: Assets con licencia compatible | C11: Factibilidad | D11: 0.1 | E11: Conseguir o hacer arte CC0/MIT/OFL coherente. | F11: datum | G11: + | H11: - | I11: =IF(G11="+",1,IF(G11="-",-1,0))*$D11 -> 0.1 | J11: =IF(H11="+",1,IF(H11="-",-1,0))*$D11 -> -0.1 | K11: El plano técnico se dibuja con líneas; casi no necesita assets. | L11: Un set de pixel art coherente con drones y retrato es difícil de juntar de paquetes CC0; más arte a mano.
A12: F4 | B12: Escalabilidad a 5 niveles | C12: Factibilidad | D12: 0.1 | E12: Costo de agregar una máquina o nivel nuevo. | F12: datum | G12: + | H12: - | I12: =IF(G12="+",1,IF(G12="-",-1,0))*$D12 -> 0.1 | J12: =IF(H12="+",1,IF(H12="-",-1,0))*$D12 -> -0.1 | K12: Una máquina nueva es un dibujo de líneas. | L12: Cada máquina nueva en pixel art necesita sprites y animación propios.
A14: Suma de pesos (debe ser 100%) | B14: =SUM(D5:D12) -> 1
A15: Peso de deseabilidad (regla: ≥ 40%) | B15: =SUMIF(C5:C12,"Deseabilidad",D5:D12) -> 0.55
A16: ¿Cumple la regla de deseabilidad? | B16: =IF(B15>=0.4,"Sí","No") -> Sí
A17: Puntuación ponderada C1 (datum) | B17: =0 -> 0
A18: Puntuación ponderada C2 | B18: =SUM(I5:I12) -> -0.6
A19: Puntuación ponderada C3 | B19: =SUM(J5:J12) -> -0.4
A20: Ganador | B20: =IF(MAX(B17:B19)=B17,"C1 — Planta en corte",IF(MAX(B17:B19)=B18,"C2 — Sala de control","C3 — Primer turno")) -> C1 — Planta en corte
A22: Sensibilidad
A23: ¿Y si en el render de C3 se agregan las etiquetas de pin (D1 y D2 de C3 pasan a S)?
A24: Puntuación C3 en ese escenario | B24: =B19-J5-J6 -> -0.1
A25: ¿Sigue ganando el datum? | B25: =IF(B24<0,"Sí: C3 pierde por factibilidad (F1, F3, F4)","No") -> Sí: C3 pierde por factibilidad (F1, F3, F4)
A27: Notas
A28: · Evidencia: evaluación de los 6 renders hecha por José Carlos el 1-oct-2026 (C3 el que más gustó; C1 el más claro en pin↔máquina y en estado; C2 el que menos). Falta la opinión de Yael y la prueba con 3–4 personas del segmento.
A29: · Horas: suma de las estimaciones gruesas de la tabla morfológica (Prompt 1); no están medidas.
A30: · Rendimiento en la PC mínima no se incluyó como criterio: los tres conceptos son 2D y empatarían (S).

Sheet Evaluación renders
A1: Imagen | B1: Concepto | C1: ¿Se entiende qué pin mueve qué? | D1: ¿Se ve el estado de un vistazo? | E1: ¿Se siente juego o clase? | F1: Problemas detectados en el render (Claude)
A2: c1-menu.jpg | B2: C1 | C2: — | D2: — | E2: Claro; 'Continuar' es la acción dominante | F2: Fondo con brazo robótico y CNC que no están en el nivel 1 (no es grave).
A3: c1-nivel1.jpg | B3: C1 | C3: Sí — el más claro (etiquetas D5/D2/D4 junto a cada máquina) | D3: Sí — el más claro (LEDs verdes + contador) | E3: Entre juego y herramienta | F3: La lámpara D2 está encendida aunque el código solo escribe el pin 5: el render contradice al código. El ícono del copiloto se parece al logo de Microsoft Copilot: no usar algo parecido.
A4: c2-menu.jpg | B4: C2 | C4: — | D4: — | E4: Se siente frío / técnico | F4: Bien legible; acentos correctos.
A5: c2-nivel1.jpg | B5: C2 | C5: Más o menos — etiquetas lejos de las máquinas | D5: Más o menos — 'todo gris' no se lee como 'todo bien' | E5: Clase / diagrama — el que menos gustó | F5: La traza de D5 sale como pulso aunque el pin está en HIGH; D4 tiene traza aunque no se usa; 'deberia' sin acento; no hay drones en pantalla.
A6: c3-menu.jpg | B6: C3 | C6: — | D6: — | E6: Juego — el que más gustó | F6: Los chasis de la banda parecen camionetas, no drones: corregir con instrucción de seguimiento.
A7: c3-nivel1.jpg | B7: C3 | C7: Más o menos — el nombre MOTOR_BANDA está en el código pero el motor no tiene etiqueta | D7: Sí, después de C1 (tablero '3 de 3', motor iluminado) | E7: Juego — el que más gustó | F7: Falta la etiqueta D5 / MOTOR_BANDA junto al motor. El personaje se ve profesional, no infantil.
A9: Fuente: evaluación de José Carlos (1-oct-2026) sobre las imágenes generadas con Google AI Studio; columna F = observaciones de Claude.

Sheet Ronda 2 (híbrido)
A1: Ronda 2 — Concepto final (arte de C3 + funciones de C1) contra el datum C1
A2: Decisión del equipo (José Carlos y Yael, 1-oct-2026). Pesos tomados de la pestaña 'Matriz de Pugh' (no se cambiaron).
A4: ID | B4: Criterio | C4: Peso | D4: Concepto final vs. C1 | E4: Puntos | F4: Justificación
A5: ='Matriz de Pugh'!A5 -> D1 | B5: ='Matriz de Pugh'!B5 -> Pin ↔ máquina legible | C5: ='Matriz de Pugh'!D5 -> 0.15 | D5: S | E5: =IF(D5="+",1,IF(D5="-",-1,0))*C5 -> 0 | F5: Mismas etiquetas de pin que C1, ahora con el nombre de la constante (D5 · MOTOR_BANDA).
A6: ='Matriz de Pugh'!A6 -> D2 | B6: ='Matriz de Pugh'!B6 -> Estado visible de un vistazo | C6: ='Matriz de Pugh'!D6 -> 0.15 | D6: + | E6: =IF(D6="+",1,IF(D6="-",-1,0))*C6 -> 0.15 | F6: LEDs de C1 + mini-trazas y marcador de desviación de C2 + objetivos con palomita.
A7: ='Matriz de Pugh'!A7 -> D3 | B7: ='Matriz de Pugh'!B7 -> Se siente juego, no clase | C7: ='Matriz de Pugh'!D7 -> 0.15 | D7: + | E7: =IF(D7="+",1,IF(D7="-",-1,0))*C7 -> 0.15 | F7: Estilo de C3, el que prefirieron ambos integrantes.
A8: ='Matriz de Pugh'!A8 -> D4 | B8: ='Matriz de Pugh'!B8 -> Primeros 30 s sin instrucciones | C8: ='Matriz de Pugh'!D8 -> 0.1 | D8: + | E8: =IF(D8="+",1,IF(D8="-",-1,0))*C8 -> 0.1 | F8: Arranque al 90% de C3: una línea y una sola acción resaltada.
A9: ='Matriz de Pugh'!A9 -> F1 | B9: ='Matriz de Pugh'!B9 -> Horas de producción | C9: ='Matriz de Pugh'!D9 -> 0.15 | D9: - | E9: =IF(D9="+",1,IF(D9="-",-1,0))*C9 -> -0.15 | F9: ~95 h vs. ~67 h del datum (pixel art + retrato + extras).
A10: ='Matriz de Pugh'!A10 -> F2 | B10: ='Matriz de Pugh'!B10 -> Riesgo técnico en Godot 4 | C10: ='Matriz de Pugh'!D10 -> 0.1 | D10: S | E10: =IF(D10="+",1,IF(D10="-",-1,0))*C10 -> 0 | F10: Mismos sistemas que C1; el marcador de desviación reutiliza el validador del nivel (RF-03).
A11: ='Matriz de Pugh'!A11 -> F3 | B11: ='Matriz de Pugh'!B11 -> Assets con licencia compatible | C11: ='Matriz de Pugh'!D11 -> 0.1 | D11: - | E11: =IF(D11="+",1,IF(D11="-",-1,0))*C11 -> -0.1 | F11: Pixel art coherente requiere más arte a mano que el vectorial.
A12: ='Matriz de Pugh'!A12 -> F4 | B12: ='Matriz de Pugh'!B12 -> Escalabilidad a 5 niveles | C12: ='Matriz de Pugh'!D12 -> 0.1 | D12: - | E12: =IF(D12="+",1,IF(D12="-",-1,0))*C12 -> -0.1 | F12: Cada máquina nueva necesita sprite propio de 32×32.
B14: Puntuación del concepto final | E14: =SUM(E5:E12) -> 0.05
B15: Resultado | E15: =IF(E14>0,"Supera al datum",IF(E14=0,"Empata con el datum","Pierde contra el datum")) -> Supera al datum
A17: Costo-beneficio (decisión consciente)
A18: · Sabemos que el pixel art cuesta ~28 h más que el vectorial y que escala peor (F1, F3, F4 en contra). Lo elegimos porque 'se siente juego, no clase' pesa 15% y es lo que el segmento pidió en las entrevistas.
A19: · Mitigación: paleta limitada de 16 colores, una sola hoja de sprites de máquinas de 32×32, base de assets CC0 retocada, y tope: si el arte del nivel 1 pasa de 30 h, las máquinas de los niveles 4–5 se reutilizan recoloreadas.
A20: · El margen es pequeño (+5): depende de controlar las horas de arte. Revisar en la semana 8.
